{
    "require": {
        "bedezign/yii2-audit": "^1.0.7",
        "dmstr/yii2-cms-metapackage": "^6.0.0",
        "dmstr/yii2-libs-metapackage": "^0.3",
        "franciscomaya/yii2-sceditor": "dev-master",
        "hrzg/yii2-cms-metapackage": "^0.7.0",
        "thomaspark/bootswatch": "^3.3",
        "vlucas/phpdotenv": "2.*",
        "yiisoft/yii2": "^2.0.8",
        "yiisoft/yii2-bootstrap": "2.*"
    },
    "require-dev": {
        "dmstr/yii2-cms-dev-metapackage": "^1.1.2"
    },
    "repositories": {
        "hrzg-private": {
            "type": "composer",
            "url": "https://toran.hrzg.de/repo/private/"
        }
    }
}